transformcl.py
transformcl-2025.1.dist-info/METADATA
transformcl-2025.1.dist-info/WHEEL
transformcl-2025.1.dist-info/licenses/LICENSE
transformcl-2025.1.dist-info/RECORD
