Metadata-Version: 2.4
Name: transformcl
Version: 2025.1
Summary: Transform angular power spectra and correlation functions
Project-URL: Documentation, https://glass.readthedocs.io/projects/transformcl
Project-URL: Repository, https://github.com/glass-dev/transformcl
Project-URL: Issues, https://github.com/glass-dev/transformcl/issues
Maintainer-email: Nicolas Tessore <n.tessore@ucl.ac.uk>
License: MIT
License-File: LICENSE
Classifier: License :: OSI Approved :: MIT License
Classifier: Operating System :: OS Independent
Classifier: Programming Language :: Python :: 3
Requires-Python: >=3.9
Requires-Dist: array-api-compat
Requires-Dist: flt>=2025.1
Provides-Extra: doc
Requires-Dist: furo; extra == 'doc'
Requires-Dist: numpydoc; extra == 'doc'
Requires-Dist: sphinx; extra == 'doc'
Requires-Dist: sphinxcontrib-katex; extra == 'doc'
